newsgather/.DS_Store
newsgather/__init__.py
newsgather/data/.DS_Store
newsgather/data/newscatcher_package_v2.db
newsgather/data/package_rss.db
newsgather-0.2.0.dist-info/METADATA
newsgather-0.2.0.dist-info/WHEEL
newsgather-0.2.0.dist-info/RECORD
