Metadata-Version: 2.1
Name: newsgather
Version: 0.2.0
Summary: Get the normalized latest news from (almost) any website
Home-page: https://www.newscatcherapi.com
License: MIT
Keywords: News,RSS,Scraping,Data Mining
Author: Artem Bugara
Author-email: bugara.artem@gmail.com
Requires-Python: >=3.7,<4.0
Classifier: License :: OSI Approved :: MIT License
Classifier: Programming Language :: Python :: 3
Classifier: Programming Language :: Python :: 3.7
Classifier: Programming Language :: Python :: 3.8
Classifier: Programming Language :: Python :: 3.9
Classifier: Programming Language :: Python :: 3.10
Classifier: Programming Language :: Python :: 3.11
Requires-Dist: feedparser (>=6.0.7,<7.0.0)
Requires-Dist: requests (>=2.23.0,<3.0.0)
